README.md
setup.py
xzy_db/__init__.py
xzy_db.egg-info/PKG-INFO
xzy_db.egg-info/SOURCES.txt
xzy_db.egg-info/dependency_links.txt
xzy_db.egg-info/requires.txt
xzy_db.egg-info/top_level.txt
xzy_db/api/__init__.py
xzy_db/api/get_fund_data.py
xzy_db/api/get_fund_list.py
xzy_db/api/get_index_data.py
xzy_db/api/get_index_weight.py
xzy_db/api/get_industry.py
xzy_db/api/get_ret.py
xzy_db/api/get_universe.py
xzy_db/crawler/__init__.py
xzy_db/crawler/futures/__init__.py
xzy_db/crawler/futures/domestic.py
xzy_db/crawler/futures/domestic_cons.py
xzy_db/hk_sangreal_calendar/__init__.py
xzy_db/sangreal_calendar/__init__.py
xzy_db/utils/__init__.py
xzy_db/utils/commons.py
xzy_db/utils/datetime_handle.py
xzy_db/utils/engines.py
xzy_db/utils/fund_type.py