Metadata-Version: 1.1
Name: xzy-db
Version: 0.0.7
Summary: short cut api for wind
Home-page: https://gitee.com/liubola/xzy-db
Author: liubola
Author-email: lby3523@gmail.com
License: GNU General Public License v3.0
Platform: all
Classifier: Operating System :: OS Independent
Classifier: Intended Audience :: Developers
Classifier: License :: OSI Approved :: GNU General Public License v3 (GPLv3)
Classifier: Programming Language :: Python :: 3.6
Classifier: Topic :: Software Development :: Libraries
